[
  {
    "market_name": "communityfarmersmarket.rutgers.edu",
    "market_url": "https://communityfarmersmarket.rutgers.edu/",
    "vendor_pages_found": [],
    "vendors": [
      {
        "name": "Rutgers Gardens\n\n\nCommunity Garden\nContact Us\nVisit Us\nRutgers Community Farm",
        "page_url": "https://communityfarmersmarket.rutgers.edu/",
        "location": null,
        "products": [],
        "contact_info": {
          "email": "lt606@njaes.rutgers.edu",
          "phone": "848-295-7690",
          "website": "https://communityfarmersmarket.rutgers.edu/"
        },
        "description": null
      },
      {
        "name": "Rutgers Community Farm",
        "page_url": "https://communityfarmersmarket.rutgers.edu/",
        "location": null,
        "products": [],
        "contact_info": {
          "email": "lt606@njaes.rutgers.edu",
          "phone": "848-295-7690",
          "website": "https://communityfarmersmarket.rutgers.edu/"
        },
        "description": null
      },
      {
        "name": "Rutgers Gardens\n\n\nCommunity Garden",
        "page_url": "https://communityfarmersmarket.rutgers.edu/",
        "location": null,
        "products": [],
        "contact_info": {
          "email": "lt606@njaes.rutgers.edu",
          "phone": "848-295-7690",
          "website": "https://communityfarmersmarket.rutgers.edu/"
        },
        "description": null
      },
      {
        "name": "Community Farm",
        "page_url": "https://communityfarmersmarket.rutgers.edu/",
        "location": null,
        "products": [],
        "contact_info": {
          "email": "lt606@njaes.rutgers.edu",
          "phone": "848-295-7690",
          "website": "https://communityfarmersmarket.rutgers.edu/"
        },
        "description": null
      },
      {
        "name": "Search Rutgers\n\n\n\nSearch\n\n\n\n\n\n\n\n\n\n\n\n\n\n\n\n\n\n\n\n\n\n\n\n\n\n\n\n\n\n\n\n\n\n\n\n\n\n\n\n\n\n\nNew Jersey Agricultural Experiment Station\nRutgers Community Farm",
        "page_url": "https://communityfarmersmarket.rutgers.edu/",
        "location": null,
        "products": [],
        "contact_info": {
          "email": "lt606@njaes.rutgers.edu",
          "phone": "848-295-7690",
          "website": "https://communityfarmersmarket.rutgers.edu/"
        },
        "description": null
      },
      {
        "name": "Rutgers Gardens",
        "page_url": "https://communityfarmersmarket.rutgers.edu/",
        "location": null,
        "products": [],
        "contact_info": {
          "email": "lt606@njaes.rutgers.edu",
          "phone": "848-295-7690",
          "website": "https://communityfarmersmarket.rutgers.edu/"
        },
        "description": null
      },
      {
        "name": "New Brunswick Community Farm",
        "page_url": "https://communityfarmersmarket.rutgers.edu/",
        "location": null,
        "products": [
          "local"
        ],
        "contact_info": {
          "email": "lt606@njaes.rutgers.edu",
          "phone": "848-295-7690",
          "website": "https://communityfarmersmarket.rutgers.edu/"
        },
        "description": null
      },
      {
        "name": "The Rutgers Community Farm",
        "page_url": "https://communityfarmersmarket.rutgers.edu/",
        "location": null,
        "products": [
          "local"
        ],
        "contact_info": {
          "email": "lt606@njaes.rutgers.edu",
          "phone": "848-295-7690",
          "website": "https://communityfarmersmarket.rutgers.edu/"
        },
        "description": null
      },
      {
        "name": "Market\nThe Rutgers Community Farm",
        "page_url": "https://communityfarmersmarket.rutgers.edu/",
        "location": null,
        "products": [
          "local"
        ],
        "contact_info": {
          "email": "lt606@njaes.rutgers.edu",
          "phone": "848-295-7690",
          "website": "https://communityfarmersmarket.rutgers.edu/"
        },
        "description": null
      },
      {
        "name": "Community Garden",
        "page_url": "https://communityfarmersmarket.rutgers.edu/",
        "location": null,
        "products": [],
        "contact_info": {},
        "description": "Community Garden"
      }
    ],
    "processing_time": 0.1699681282043457,
    "error": null
  },
  {
    "market_name": "cowtownfarmersmarket.com",
    "market_url": "https://cowtownfarmersmarket.com/",
    "vendor_pages_found": [
      {
        "text": "featured vendors",
        "url": "https://www.cowtownfarmersmarket.com/vendors/?vc=453",
        "indicator": "vendors",
        "priority": 2
      }
    ],
    "vendors": [
      {
        "name": "Cowtown Farm",
        "page_url": "https://cowtownfarmersmarket.com/",
        "location": null,
        "products": [],
        "contact_info": {
          "phone": "856-769-3000",
          "website": "https://www.cowtownfarmersmarket.com/"
        },
        "description": null
      },
      {
        "name": "Unitech Inc",
        "page_url": "https://www.cowtownfarmersmarket.com/vendors/?vc=453",
        "location": null,
        "products": [],
        "contact_info": {
          "email": "howardsclothing@gmail.com",
          "phone": "(484)437-4715",
          "website": "https://www.cowtownfarmersmarket.com/"
        },
        "description": null
      },
      {
        "name": "The Cowtown Farm",
        "page_url": "https://www.cowtownfarmersmarket.com/vendors/?vc=453",
        "location": null,
        "products": [],
        "contact_info": {
          "email": "howardsclothing@gmail.com",
          "phone": "(484)437-4715",
          "website": "https://www.cowtownfarmersmarket.com/"
        },
        "description": null
      },
      {
        "name": "Pretzel Bakery",
        "page_url": "https://www.cowtownfarmersmarket.com/vendors/?vc=453",
        "location": null,
        "products": [],
        "contact_info": {
          "email": "howardsclothing@gmail.com",
          "phone": "(484)437-4715",
          "website": "https://www.cowtownfarmersmarket.com/"
        },
        "description": null
      }
    ],
    "processing_time": 4.212421894073486,
    "error": null
  },
  {
    "market_name": "cropsnj.org",
    "market_url": "https://cropsnj.org/access-food",
    "vendor_pages_found": [],
    "vendors": [
      {
        "name": "No Farm",
        "page_url": "https://cropsnj.org/access-food",
        "location": null,
        "products": [
          "produce"
        ],
        "contact_info": {
          "phone": "(609) 412-5046"
        },
        "description": null
      },
      {
        "name": "Open Menu\nClose Menu\n\n\n\n\n\n\n\n\n\n\n\n\n\n\n\n\n\n\n\n\n        About\n      \n\n\n\n\n        Programs\n      \n\n\n\n\n\n                  Cultivating Fresh Produce",
        "page_url": "https://cropsnj.org/access-food",
        "location": null,
        "products": [
          "fresh",
          "produce"
        ],
        "contact_info": {
          "phone": "(609) 412-5046"
        },
        "description": null
      },
      {
        "name": "Programs\n\n\n\n\n\n\n\nBack\n\n\n\n\n\n                        Cultivating Fresh Produce",
        "page_url": "https://cropsnj.org/access-food",
        "location": null,
        "products": [
          "fresh",
          "produce"
        ],
        "contact_info": {
          "phone": "(609) 412-5046"
        },
        "description": null
      },
      {
        "name": "Food\n                \n\n\n\n\n\n                  Farm",
        "page_url": "https://cropsnj.org/access-food",
        "location": null,
        "products": [],
        "contact_info": {
          "phone": "(609) 412-5046"
        },
        "description": null
      },
      {
        "name": "Food\n\n\n\n\n\n\n\n\n\n\n\n\n\n\n\n\n\n\n\n\n\n\n\n\n\n\n\n\n\n\n\n\n\n\n\n\n\n\n\n\n\n\n\n\n\n\nFarm",
        "page_url": "https://cropsnj.org/access-food",
        "location": null,
        "products": [
          "local",
          "vegetables",
          "herbs"
        ],
        "contact_info": {
          "phone": "(609) 412-5046"
        },
        "description": null
      },
      {
        "name": "Park Community Garden Farm",
        "page_url": "https://cropsnj.org/access-food",
        "location": null,
        "products": [],
        "contact_info": {
          "phone": "(609) 412-5046"
        },
        "description": null
      },
      {
        "name": "Park Community Garden",
        "page_url": "https://cropsnj.org/access-food",
        "location": null,
        "products": [],
        "contact_info": {
          "phone": "(609) 412-5046"
        },
        "description": null
      },
      {
        "name": "Nutritious Food\n                      \n\n\n\n\n\n                        Farm",
        "page_url": "https://cropsnj.org/access-food",
        "location": null,
        "products": [],
        "contact_info": {
          "phone": "(609) 412-5046"
        },
        "description": null
      },
      {
        "name": "Food\n                      \n\n\n\n\n\n                        Farm",
        "page_url": "https://cropsnj.org/access-food",
        "location": null,
        "products": [],
        "contact_info": {
          "phone": "(609) 412-5046"
        },
        "description": null
      },
      {
        "name": "Nutritious Food\n                \n\n\n\n\n\n                  Farm",
        "page_url": "https://cropsnj.org/access-food",
        "location": null,
        "products": [],
        "contact_info": {
          "phone": "(609) 412-5046"
        },
        "description": null
      },
      {
        "name": "Content\n      \n\n\n\n\n\n\n\n\n\n\n\n\n\n\n\n\n        About\n      \n\n\n\n\n        Programs\n      \n\n\n\n\n\n                  Cultivating Fresh Produce",
        "page_url": "https://cropsnj.org/access-food",
        "location": null,
        "products": [
          "fresh",
          "produce"
        ],
        "contact_info": {
          "phone": "(609) 412-5046"
        },
        "description": null
      },
      {
        "name": "Garden Farm",
        "page_url": "https://cropsnj.org/access-food",
        "location": null,
        "products": [],
        "contact_info": {
          "phone": "(609) 412-5046"
        },
        "description": null
      },
      {
        "name": "Nutritious Food\n\n\n\n\n\n\n\n\n\n\n\n\n\n\n\n\n\n\n\n\n\n\n\n\n\n\n\n\n\n\n\n\n\n\n\n\n\n\n\n\n\n\n\n\n\n\nFarm",
        "page_url": "https://cropsnj.org/access-food",
        "location": null,
        "products": [
          "local",
          "vegetables",
          "herbs"
        ],
        "contact_info": {
          "phone": "(609) 412-5046"
        },
        "description": null
      }
    ],
    "processing_time": 0.888556957244873,
    "error": null
  },
  {
    "market_name": "denvillefarmersmarket.com",
    "market_url": "https://denvillefarmersmarket.com/",
    "vendor_pages_found": [],
    "vendors": [],
    "processing_time": 0,
    "error": "Failed to fetch main page"
  },
  {
    "market_name": "dooww.com",
    "market_url": "https://dooww.com/farmersmarket",
    "vendor_pages_found": [
      {
        "text": "farmers market",
        "url": "https://www.dooww.com/farmersmarket",
        "indicator": "farmers",
        "priority": 2
      },
      {
        "text": "farmers market vendor application",
        "url": "https://www.dooww.com/_files/ugd/da89b2_a2ac8c2202dd481e9ab240e8ce424309.pdf",
        "indicator": "farmers",
        "priority": 2
      }
    ],
    "vendors": [
      {
        "name": "The Downtown Wildwood Farm",
        "page_url": "https://dooww.com/farmersmarket",
        "location": null,
        "products": [],
        "contact_info": {
          "email": "Joanne.boardwalk@gmail.com",
          "phone": "609-523-1602",
          "website": "https://www.dooww.com/farmersmarket"
        },
        "description": null
      },
      {
        "name": "Wildwood Farm",
        "page_url": "https://dooww.com/farmersmarket",
        "location": null,
        "products": [],
        "contact_info": {
          "email": "Joanne.boardwalk@gmail.com",
          "phone": "609-523-1602",
          "website": "https://www.dooww.com/farmersmarket"
        },
        "description": null
      },
      {
        "name": "Downtown Farm",
        "page_url": "https://dooww.com/farmersmarket",
        "location": null,
        "products": [],
        "contact_info": {
          "email": "Joanne.boardwalk@gmail.com",
          "phone": "609-523-1602",
          "website": "https://www.dooww.com/farmersmarket"
        },
        "description": null
      },
      {
        "name": "Downtown Wildwood Farm",
        "page_url": "https://dooww.com/farmersmarket",
        "location": null,
        "products": [],
        "contact_info": {
          "email": "Joanne.boardwalk@gmail.com",
          "phone": "609-523-1602",
          "website": "https://www.dooww.com/farmersmarket"
        },
        "description": null
      }
    ],
    "processing_time": 6.040595054626465,
    "error": null
  },
  {
    "market_name": "downtownclifton.com",
    "market_url": "https://downtownclifton.com/",
    "vendor_pages_found": [],
    "vendors": [],
    "processing_time": 0.2996218204498291,
    "error": null
  },
  {
    "market_name": "downtowntomsriver.com",
    "market_url": "https://downtowntomsriver.com/farmersmarket",
    "vendor_pages_found": [],
    "vendors": [],
    "processing_time": 0,
    "error": "Failed to fetch main page"
  },
  {
    "market_name": "englishtownauction.com",
    "market_url": "https://englishtownauction.com/",
    "vendor_pages_found": [],
    "vendors": [
      {
        "name": "Aquarius Designs Inc",
        "page_url": "https://englishtownauction.com/",
        "location": null,
        "products": [],
        "contact_info": {
          "phone": "732-446-9644"
        },
        "description": null
      }
    ],
    "processing_time": 0.11281180381774902,
    "error": null
  },
  {
    "market_name": "facebook.com",
    "market_url": "https://facebook.com/WayneYNJFarmersMarket",
    "vendor_pages_found": [],
    "vendors": [],
    "processing_time": 0,
    "error": "Failed to fetch main page"
  },
  {
    "market_name": "facebook.com",
    "market_url": "https://facebook.com/vernontwpfarmersmarket",
    "vendor_pages_found": [],
    "vendors": [],
    "processing_time": 0,
    "error": "Failed to fetch main page"
  }
]